{"id": "e0b01edd-d21e-4049-84d1-43defae4d407", "type": "dataset", "server": "https://api.resourcewatch.org", "attributes": {"name": "MODIS Fire Alerts Whitelist - GADM Adm2 level - v20200429", "slug": "MODIS-Fire-Alerts-Whitelist-GADM-Adm2-level-v20200429_1", "type": null, "subtitle": null, "application": ["gfw"], "dataPath": null, "attributesPath": null, "connectorType": "document", "provider": "tsv", "userId": "5c65c4b9529ae7001113fd06", "connectorUrl": null, "sources": ["https://gfw-pipelines-staging.s3.amazonaws.com/geotrellis/results/firealerts_gadm_modis_2020-05-13/2020-05-13/firealerts_modis_20200513_1850/adm2/whitelist/part-00000-0a25aa7d-b04d-4c51-89b4-0786890988e4-c000.csv"], "tableName": "index_e0b01eddd21e404984d143defae4d407_1594067693201", "status": "saved", "published": true, "overwrite": true, "mainDateField": null, "env": "production", "geoInfo": false, "protected": false, "legend": {"date": [], "region": [], "country": [], "nested": [], "integer": [], "short": [], "byte": [], "double": [], "float": [], "half_float": [], "scaled_float": [], "boolean": [], "binary": [], "text": [], "keyword": ["iso", "adm1", "adm2", "wdpa_protected_area__iucn_cat", "is__umd_regional_primary_forest_2001", "is__birdlife_alliance_for_zero_extinction_site", "is__birdlife_key_biodiversity_area", "is__landmark_land_right", "gfw_plantation__type", "is__gfw_mining", "is__gfw_managed_forest", "rspo_oil_palm__certification_status", "is__gfw_wood_fiber", "is__peatland", "is__idn_forest_moratorium", "is__gfw_oil_palm", "idn_forest_area__type", "per_forest_concession__type", "is__gfw_oil_gas", "is__gmw_mangroves_2016", "is__ifl_intact_forest_landscape_2016", "bra_biome__name"]}, "clonedHost": {}, "errorMessage": "", "taskId": "/v1/doc-importer/task/653b9cb5-c7ae-4307-ac87-f60dc4207b45", "createdAt": "2020-07-06T20:34:44.017Z", "updatedAt": "2020-07-06T20:36:19.136Z", "dataLastUpdated": null, "metadata": [], "widget": [], "layer": [], "vocabulary": [], "widgetRelevantProps": [], "layerRelevantProps": []}}